partial_index/__init__.py
partial_index/index.py
partial_index/mixins.py
partial_index/query.py
django_partial_index-0.6.0.dist-info/LICENSE.txt
django_partial_index-0.6.0.dist-info/METADATA
django_partial_index-0.6.0.dist-info/WHEEL
django_partial_index-0.6.0.dist-info/top_level.txt
django_partial_index-0.6.0.dist-info/RECORD
