Metadata-Version: 2.1
Name: django-partial-index
Version: 0.6.0
Summary: PostgreSQL and SQLite partial indexes for Django models
Home-page: https://github.com/mattiaslinnap/django-partial-index
Author: Mattias Linnap
Author-email: mattias@linnap.com
License: BSD
Download-URL: https://github.com/mattiaslinnap/django-partial-index/archive/0.6.0.tar.gz
Platform: UNKNOWN
Classifier: Development Status :: 4 - Beta
Classifier: Environment :: Web Environment
Classifier: Framework :: Django
Classifier: Framework :: Django :: 1.11
Classifier: Framework :: Django :: 2.0
Classifier: Framework :: Django :: 2.1
Classifier: Framework :: Django :: 2.2
Classifier: Intended Audience :: Developers
Classifier: License :: OSI Approved :: BSD License
Classifier: Operating System :: OS Independent
Classifier: Programming Language :: Python
Classifier: Programming Language :: Python :: 2
Classifier: Programming Language :: Python :: 2.7
Classifier: Programming Language :: Python :: 3
Classifier: Programming Language :: Python :: 3.4
Classifier: Programming Language :: Python :: 3.5
Classifier: Programming Language :: Python :: 3.6
Classifier: Topic :: Database
Classifier: Topic :: Internet :: WWW/HTTP
